myoutput/__init__.py
myoutput/myoutput.py
myoutput-0.0.2.dist-info/METADATA
myoutput-0.0.2.dist-info/WHEEL
myoutput-0.0.2.dist-info/licenses/LICENSE
myoutput-0.0.2.dist-info/RECORD
