Metadata-Version: 2.4
Name: myoutput
Version: 0.0.2
Summary: Allows users customization of output colour, spacing, and more
Project-URL: Homepage, https://github.com/crophes/myoutput
Project-URL: Issues, https://github.com/crophes/myoutput/issues
Author-email: Crophes <crophes+python_package@gmail.com>
License-Expression: MIT
License-File: LICENSE
Classifier: Intended Audience :: Developers
Classifier: License :: OSI Approved :: MIT License
Classifier: Programming Language :: Python :: 3
Classifier: Topic :: Software Development :: Libraries
Classifier: Topic :: Utilities
Requires-Python: >=3.9
